{
	"id": "606f4722-e86c-439e-9d26-e833bda5f767",
	"name": "atlas-h2020-variables",
	"values": [
		{
			"key": "field_data_url",
			"value": "https://staging.atlas.agricircle.com/api/h2020/field",
			"type": "default",
			"enabled": true
		},
		{
			"key": "field_data_token",
			"value": "",
			"type": "secret",
			"enabled": true
		},
		{
			"key": "field_urn",
			"value": "urn:com.agricircle.atlas.field_data:9f12f4ef-0000-0000-0000-000000000001",
			"type": "default",
			"enabled": true
		},
		{
			"key": "advice_urn",
			"value": "",
			"type": "default",
			"enabled": true
		},
		{
			"key": "advice_application_ref",
			"value": "",
			"type": "default",
			"enabled": true
		},
		{
			"key": "crop_protection_advisor_url",
			"value": "https://staging.atlas.agricircle.com/api/h2020/crop_protection",
			"type": "default",
			"enabled": true
		},
		{
			"key": "crop_protection_advisor_token",
			"value": "",
			"type": "secret",
			"enabled": true
		},
		{
			"key": "fertilisation_advisor_url",
			"value": "https://staging.atlas.agricircle.com/api/h2020/fertilisation_advisor",
			"type": "default",
			"enabled": true
		},
		{
			"key": "fertilisation_advisor_token",
			"value": "",
			"type": "secret",
			"enabled": true
		},
		{
			"key": "sowing_advisor_url",
			"value": "https://staging.atlas.agricircle.com/api/h2020/sowing",
			"type": "default",
			"enabled": true
		},
		{
			"key": "sowing_advisor_token",
			"value": "",
			"type": "secret",
			"enabled": true
		},
		{
			"key": "harvesting_advisor_url",
			"value": "https://staging.atlas.agricircle.com/api/h2020/harvesting",
			"type": "default",
			"enabled": true
		},
		{
			"key": "harvesting_advisor_token",
			"value": "",
			"type": "secret",
			"enabled": true
		},
		{
			"key": "irrigation_advisor_url",
			"value": "",
			"type": "default",
			"enabled": true
		},
		{
			"key": "irrigation_advisor_token",
			"value": "",
			"type": "secret",
			"enabled": true
		},
		{
			"key": "field_monitoring_url",
			"value": "",
			"type": "default",
			"enabled": true
		},
		{
			"key": "field_monitoring_token",
			"value": "",
			"type": "secret",
			"enabled": true
		},
		{
			"key": "machine_tracking_url",
			"value": "",
			"type": "default",
			"enabled": true
		},
		{
			"key": "machine_tracking_token",
			"value": "",
			"type": "secret",
			"enabled": true
		},
		{
			"key": "sensor_data_url",
			"value": "",
			"type": "default",
			"enabled": true
		},
		{
			"key": "sensor_data_token",
			"value": "",
			"type": "secret",
			"enabled": true
		},
		{
			"key": "temperature_monitoring_url",
			"value": "",
			"type": "default",
			"enabled": true
		},
		{
			"key": "temperature_monitoring_token",
			"value": "",
			"type": "secret",
			"enabled": true
		},
		{
			"key": "asset_tracking_url",
			"value": "",
			"type": "default",
			"enabled": true
		},
		{
			"key": "asset_tracking_token",
			"value": "",
			"type": "secret",
			"enabled": true
		},
		{
			"key": "produce_demand_forecaster_url",
			"value": "",
			"type": "default",
			"enabled": true
		},
		{
			"key": "produce_demand_forecaster_token",
			"value": "",
			"type": "secret",
			"enabled": true
		},
		{
			"key": "field_survey_url",
			"value": "",
			"type": "default",
			"enabled": true
		},
		{
			"key": "field_survey_token",
			"value": "",
			"type": "default",
			"enabled": true
		},
		{
			"key": "equipment_centre_token",
			"value": "",
			"type": "default",
			"enabled": true
		}
	],
	"_postman_variable_scope": "environment",
	"_postman_exported_at": "2023-01-17T13:35:48.558Z",
	"_postman_exported_using": "Postman/10.8.0"
}